{
  "checked_at": "2026-06-06 20:33:26 UTC",
  "total_working": 714,
  "avg_latency_ms": 643.5,
  "min_latency_ms": 35,
  "avg_speed_mbps": 0,
  "speed_checked": false,
  "countries": {
    "AE": {
      "count": 1,
      "avg_ping_ms": 963.0
    },
    "AL": {
      "count": 2,
      "avg_ping_ms": 797.0
    },
    "AM": {
      "count": 1,
      "avg_ping_ms": 1278.0
    },
    "AT": {
      "count": 4,
      "avg_ping_ms": 845.8
    },
    "AU": {
      "count": 4,
      "avg_ping_ms": 1165.5
    },
    "BE": {
      "count": 3,
      "avg_ping_ms": 392.0
    },
    "BG": {
      "count": 2,
      "avg_ping_ms": 1137.0
    },
    "CA": {
      "count": 27,
      "avg_ping_ms": 289.0
    },
    "CH": {
      "count": 4,
      "avg_ping_ms": 949.5
    },
    "CL": {
      "count": 1,
      "avg_ping_ms": 673.0
    },
    "CN": {
      "count": 3,
      "avg_ping_ms": 698.3
    },
    "CO": {
      "count": 3,
      "avg_ping_ms": 623.3
    },
    "CZ": {
      "count": 3,
      "avg_ping_ms": 690.0
    },
    "DE": {
      "count": 84,
      "avg_ping_ms": 629.7
    },
    "EE": {
      "count": 2,
      "avg_ping_ms": 597.5
    },
    "ES": {
      "count": 5,
      "avg_ping_ms": 514.2
    },
    "FI": {
      "count": 42,
      "avg_ping_ms": 843.0
    },
    "FR": {
      "count": 41,
      "avg_ping_ms": 690.2
    },
    "GB": {
      "count": 56,
      "avg_ping_ms": 627.2
    },
    "GE": {
      "count": 3,
      "avg_ping_ms": 514.3
    },
    "GR": {
      "count": 1,
      "avg_ping_ms": 879.0
    },
    "HK": {
      "count": 12,
      "avg_ping_ms": 881.6
    },
    "HU": {
      "count": 19,
      "avg_ping_ms": 777.8
    },
    "IE": {
      "count": 1,
      "avg_ping_ms": 802.0
    },
    "IL": {
      "count": 3,
      "avg_ping_ms": 910.3
    },
    "IN": {
      "count": 4,
      "avg_ping_ms": 1055.0
    },
    "IR": {
      "count": 1,
      "avg_ping_ms": 921.0
    },
    "IT": {
      "count": 28,
      "avg_ping_ms": 841.1
    },
    "JP": {
      "count": 23,
      "avg_ping_ms": 837.7
    },
    "KR": {
      "count": 13,
      "avg_ping_ms": 1035.2
    },
    "LT": {
      "count": 1,
      "avg_ping_ms": 664.0
    },
    "LU": {
      "count": 1,
      "avg_ping_ms": 503.0
    },
    "LV": {
      "count": 4,
      "avg_ping_ms": 964.5
    },
    "MD": {
      "count": 2,
      "avg_ping_ms": 616.0
    },
    "MX": {
      "count": 3,
      "avg_ping_ms": 392.3
    },
    "MY": {
      "count": 2,
      "avg_ping_ms": 1277.5
    },
    "NL": {
      "count": 87,
      "avg_ping_ms": 611.4
    },
    "NO": {
      "count": 5,
      "avg_ping_ms": 681.6
    },
    "PH": {
      "count": 2,
      "avg_ping_ms": 905.0
    },
    "PK": {
      "count": 1,
      "avg_ping_ms": 571.0
    },
    "PL": {
      "count": 8,
      "avg_ping_ms": 723.0
    },
    "RO": {
      "count": 4,
      "avg_ping_ms": 683.0
    },
    "RS": {
      "count": 2,
      "avg_ping_ms": 929.5
    },
    "RU": {
      "count": 13,
      "avg_ping_ms": 801.4
    },
    "SA": {
      "count": 3,
      "avg_ping_ms": 1204.7
    },
    "SC": {
      "count": 1,
      "avg_ping_ms": 487.0
    },
    "SE": {
      "count": 12,
      "avg_ping_ms": 791.2
    },
    "SG": {
      "count": 8,
      "avg_ping_ms": 1008.0
    },
    "SK": {
      "count": 4,
      "avg_ping_ms": 597.5
    },
    "TH": {
      "count": 2,
      "avg_ping_ms": 1258.5
    },
    "TR": {
      "count": 7,
      "avg_ping_ms": 755.4
    },
    "TW": {
      "count": 3,
      "avg_ping_ms": 758.7
    },
    "US": {
      "count": 139,
      "avg_ping_ms": 359.6
    },
    "XX": {
      "count": 1,
      "avg_ping_ms": 335.0
    },
    "ZA": {
      "count": 3,
      "avg_ping_ms": 1125.7
    }
  }
}