{
  "checked_at": "2026-05-09 12:45:44 UTC",
  "total_working": 5118,
  "avg_latency_ms": 839.7,
  "min_latency_ms": 78,
  "avg_speed_mbps": 0,
  "speed_checked": false,
  "countries": {
    "AE": {
      "count": 3,
      "avg_ping_ms": 1163.0
    },
    "AL": {
      "count": 7,
      "avg_ping_ms": 1050.1
    },
    "AM": {
      "count": 1,
      "avg_ping_ms": 1157.0
    },
    "AR": {
      "count": 2,
      "avg_ping_ms": 1029.0
    },
    "AT": {
      "count": 13,
      "avg_ping_ms": 931.1
    },
    "AU": {
      "count": 5,
      "avg_ping_ms": 1112.8
    },
    "BA": {
      "count": 1,
      "avg_ping_ms": 971.0
    },
    "BE": {
      "count": 5,
      "avg_ping_ms": 777.2
    },
    "BG": {
      "count": 4,
      "avg_ping_ms": 1143.5
    },
    "BH": {
      "count": 1,
      "avg_ping_ms": 1122.0
    },
    "BO": {
      "count": 2,
      "avg_ping_ms": 966.0
    },
    "BR": {
      "count": 5,
      "avg_ping_ms": 918.6
    },
    "CA": {
      "count": 53,
      "avg_ping_ms": 718.3
    },
    "CH": {
      "count": 6,
      "avg_ping_ms": 849.0
    },
    "CL": {
      "count": 3,
      "avg_ping_ms": 646.3
    },
    "CO": {
      "count": 1,
      "avg_ping_ms": 830.0
    },
    "CY": {
      "count": 1,
      "avg_ping_ms": 860.0
    },
    "CZ": {
      "count": 4,
      "avg_ping_ms": 1118.8
    },
    "DE": {
      "count": 953,
      "avg_ping_ms": 1021.8
    },
    "DK": {
      "count": 3,
      "avg_ping_ms": 624.3
    },
    "EC": {
      "count": 3,
      "avg_ping_ms": 826.3
    },
    "EE": {
      "count": 8,
      "avg_ping_ms": 736.0
    },
    "EG": {
      "count": 2,
      "avg_ping_ms": 909.0
    },
    "ES": {
      "count": 17,
      "avg_ping_ms": 919.9
    },
    "FI": {
      "count": 129,
      "avg_ping_ms": 964.8
    },
    "FR": {
      "count": 175,
      "avg_ping_ms": 907.3
    },
    "GB": {
      "count": 327,
      "avg_ping_ms": 906.8
    },
    "GE": {
      "count": 1,
      "avg_ping_ms": 666.0
    },
    "GR": {
      "count": 1,
      "avg_ping_ms": 1111.0
    },
    "HK": {
      "count": 56,
      "avg_ping_ms": 1045.9
    },
    "HR": {
      "count": 2,
      "avg_ping_ms": 854.5
    },
    "HU": {
      "count": 4,
      "avg_ping_ms": 1021.5
    },
    "ID": {
      "count": 2,
      "avg_ping_ms": 1067.0
    },
    "IE": {
      "count": 4,
      "avg_ping_ms": 702.8
    },
    "IL": {
      "count": 1,
      "avg_ping_ms": 859.0
    },
    "IN": {
      "count": 9,
      "avg_ping_ms": 1222.7
    },
    "IS": {
      "count": 1,
      "avg_ping_ms": 1013.0
    },
    "IT": {
      "count": 13,
      "avg_ping_ms": 1065.6
    },
    "JP": {
      "count": 70,
      "avg_ping_ms": 883.8
    },
    "KH": {
      "count": 2,
      "avg_ping_ms": 1240.5
    },
    "KR": {
      "count": 26,
      "avg_ping_ms": 1086.0
    },
    "KZ": {
      "count": 1,
      "avg_ping_ms": 1428.0
    },
    "LT": {
      "count": 44,
      "avg_ping_ms": 1144.0
    },
    "LU": {
      "count": 1,
      "avg_ping_ms": 994.0
    },
    "LV": {
      "count": 23,
      "avg_ping_ms": 1124.0
    },
    "MA": {
      "count": 3,
      "avg_ping_ms": 924.0
    },
    "MK": {
      "count": 3,
      "avg_ping_ms": 1120.3
    },
    "MT": {
      "count": 2,
      "avg_ping_ms": 716.0
    },
    "MX": {
      "count": 1,
      "avg_ping_ms": 546.0
    },
    "MY": {
      "count": 5,
      "avg_ping_ms": 1300.8
    },
    "NL": {
      "count": 1421,
      "avg_ping_ms": 776.6
    },
    "OM": {
      "count": 1,
      "avg_ping_ms": 1436.0
    },
    "PA": {
      "count": 2,
      "avg_ping_ms": 611.0
    },
    "PE": {
      "count": 3,
      "avg_ping_ms": 784.0
    },
    "PK": {
      "count": 2,
      "avg_ping_ms": 1235.5
    },
    "PL": {
      "count": 76,
      "avg_ping_ms": 1017.8
    },
    "PR": {
      "count": 3,
      "avg_ping_ms": 262.0
    },
    "PT": {
      "count": 1,
      "avg_ping_ms": 617.0
    },
    "PY": {
      "count": 1,
      "avg_ping_ms": 953.0
    },
    "RO": {
      "count": 3,
      "avg_ping_ms": 956.0
    },
    "RS": {
      "count": 2,
      "avg_ping_ms": 1025.0
    },
    "RU": {
      "count": 60,
      "avg_ping_ms": 886.1
    },
    "SA": {
      "count": 3,
      "avg_ping_ms": 1365.3
    },
    "SE": {
      "count": 467,
      "avg_ping_ms": 1079.2
    },
    "SG": {
      "count": 76,
      "avg_ping_ms": 1010.7
    },
    "SI": {
      "count": 1,
      "avg_ping_ms": 727.0
    },
    "SK": {
      "count": 1,
      "avg_ping_ms": 822.0
    },
    "TH": {
      "count": 2,
      "avg_ping_ms": 1180.0
    },
    "TR": {
      "count": 9,
      "avg_ping_ms": 1029.6
    },
    "TW": {
      "count": 21,
      "avg_ping_ms": 950.9
    },
    "UA": {
      "count": 1,
      "avg_ping_ms": 1045.0
    },
    "US": {
      "count": 887,
      "avg_ping_ms": 451.5
    },
    "VN": {
      "count": 11,
      "avg_ping_ms": 1135.7
    },
    "XX": {
      "count": 47,
      "avg_ping_ms": 894.4
    },
    "ZA": {
      "count": 8,
      "avg_ping_ms": 1213.4
    }
  }
}