{
  "checked_at": "2026-07-14 14:57:16 UTC",
  "total_working": 1084,
  "avg_latency_ms": 570.3,
  "min_latency_ms": 31,
  "avg_speed_mbps": 0,
  "speed_checked": false,
  "countries": {
    "AE": {
      "count": 1,
      "avg_ping_ms": 1226.0
    },
    "AL": {
      "count": 1,
      "avg_ping_ms": 594.0
    },
    "AM": {
      "count": 1,
      "avg_ping_ms": 1325.0
    },
    "AU": {
      "count": 8,
      "avg_ping_ms": 1004.4
    },
    "BG": {
      "count": 1,
      "avg_ping_ms": 601.0
    },
    "CA": {
      "count": 69,
      "avg_ping_ms": 278.6
    },
    "CZ": {
      "count": 1,
      "avg_ping_ms": 975.0
    },
    "DE": {
      "count": 66,
      "avg_ping_ms": 651.5
    },
    "EE": {
      "count": 2,
      "avg_ping_ms": 774.5
    },
    "ES": {
      "count": 5,
      "avg_ping_ms": 637.6
    },
    "FI": {
      "count": 16,
      "avg_ping_ms": 752.0
    },
    "FR": {
      "count": 43,
      "avg_ping_ms": 583.1
    },
    "GB": {
      "count": 31,
      "avg_ping_ms": 487.0
    },
    "GE": {
      "count": 1,
      "avg_ping_ms": 681.0
    },
    "HK": {
      "count": 15,
      "avg_ping_ms": 1129.0
    },
    "ID": {
      "count": 1,
      "avg_ping_ms": 506.0
    },
    "IE": {
      "count": 6,
      "avg_ping_ms": 460.3
    },
    "IN": {
      "count": 6,
      "avg_ping_ms": 974.5
    },
    "IT": {
      "count": 18,
      "avg_ping_ms": 628.7
    },
    "JP": {
      "count": 90,
      "avg_ping_ms": 1024.2
    },
    "KR": {
      "count": 29,
      "avg_ping_ms": 1086.2
    },
    "KZ": {
      "count": 4,
      "avg_ping_ms": 1009.5
    },
    "LT": {
      "count": 4,
      "avg_ping_ms": 772.0
    },
    "LV": {
      "count": 4,
      "avg_ping_ms": 1035.2
    },
    "MY": {
      "count": 2,
      "avg_ping_ms": 1120.0
    },
    "NL": {
      "count": 127,
      "avg_ping_ms": 572.4
    },
    "NO": {
      "count": 2,
      "avg_ping_ms": 968.5
    },
    "PH": {
      "count": 2,
      "avg_ping_ms": 995.5
    },
    "PK": {
      "count": 1,
      "avg_ping_ms": 786.0
    },
    "PL": {
      "count": 22,
      "avg_ping_ms": 861.8
    },
    "RO": {
      "count": 3,
      "avg_ping_ms": 698.0
    },
    "RU": {
      "count": 37,
      "avg_ping_ms": 876.2
    },
    "SA": {
      "count": 2,
      "avg_ping_ms": 1145.0
    },
    "SC": {
      "count": 1,
      "avg_ping_ms": 1284.0
    },
    "SE": {
      "count": 11,
      "avg_ping_ms": 794.9
    },
    "SG": {
      "count": 36,
      "avg_ping_ms": 1116.4
    },
    "TR": {
      "count": 19,
      "avg_ping_ms": 681.6
    },
    "TW": {
      "count": 6,
      "avg_ping_ms": 857.7
    },
    "UA": {
      "count": 2,
      "avg_ping_ms": 502.5
    },
    "US": {
      "count": 372,
      "avg_ping_ms": 257.7
    },
    "VN": {
      "count": 1,
      "avg_ping_ms": 1367.0
    },
    "XX": {
      "count": 11,
      "avg_ping_ms": 599.5
    },
    "ZA": {
      "count": 4,
      "avg_ping_ms": 1199.2
    }
  }
}