{
  "checked_at": "2026-06-01 23:52:50 UTC",
  "total_working": 1070,
  "avg_latency_ms": 690.3,
  "min_latency_ms": 88,
  "avg_speed_mbps": 0,
  "speed_checked": false,
  "countries": {
    "AE": {
      "count": 3,
      "avg_ping_ms": 858.0
    },
    "AL": {
      "count": 4,
      "avg_ping_ms": 652.5
    },
    "AM": {
      "count": 1,
      "avg_ping_ms": 1335.0
    },
    "AT": {
      "count": 3,
      "avg_ping_ms": 1114.7
    },
    "AU": {
      "count": 7,
      "avg_ping_ms": 1262.6
    },
    "BA": {
      "count": 1,
      "avg_ping_ms": 501.0
    },
    "BG": {
      "count": 6,
      "avg_ping_ms": 953.3
    },
    "BR": {
      "count": 1,
      "avg_ping_ms": 676.0
    },
    "BY": {
      "count": 3,
      "avg_ping_ms": 715.0
    },
    "CA": {
      "count": 11,
      "avg_ping_ms": 347.3
    },
    "CH": {
      "count": 10,
      "avg_ping_ms": 837.7
    },
    "CL": {
      "count": 1,
      "avg_ping_ms": 741.0
    },
    "CN": {
      "count": 5,
      "avg_ping_ms": 831.0
    },
    "CO": {
      "count": 1,
      "avg_ping_ms": 584.0
    },
    "CZ": {
      "count": 6,
      "avg_ping_ms": 811.5
    },
    "DE": {
      "count": 102,
      "avg_ping_ms": 731.3
    },
    "DK": {
      "count": 1,
      "avg_ping_ms": 945.0
    },
    "EE": {
      "count": 2,
      "avg_ping_ms": 927.5
    },
    "EG": {
      "count": 1,
      "avg_ping_ms": 1001.0
    },
    "ES": {
      "count": 1,
      "avg_ping_ms": 504.0
    },
    "FI": {
      "count": 42,
      "avg_ping_ms": 920.5
    },
    "FR": {
      "count": 62,
      "avg_ping_ms": 771.1
    },
    "GB": {
      "count": 69,
      "avg_ping_ms": 658.9
    },
    "GE": {
      "count": 5,
      "avg_ping_ms": 691.8
    },
    "GR": {
      "count": 2,
      "avg_ping_ms": 1143.5
    },
    "HK": {
      "count": 24,
      "avg_ping_ms": 979.8
    },
    "HU": {
      "count": 2,
      "avg_ping_ms": 706.0
    },
    "IE": {
      "count": 2,
      "avg_ping_ms": 773.0
    },
    "IL": {
      "count": 1,
      "avg_ping_ms": 1080.0
    },
    "IN": {
      "count": 6,
      "avg_ping_ms": 1079.2
    },
    "IR": {
      "count": 1,
      "avg_ping_ms": 746.0
    },
    "IS": {
      "count": 1,
      "avg_ping_ms": 1085.0
    },
    "IT": {
      "count": 12,
      "avg_ping_ms": 703.5
    },
    "JP": {
      "count": 23,
      "avg_ping_ms": 688.0
    },
    "KR": {
      "count": 14,
      "avg_ping_ms": 1003.6
    },
    "KZ": {
      "count": 1,
      "avg_ping_ms": 679.0
    },
    "LK": {
      "count": 1,
      "avg_ping_ms": 908.0
    },
    "LT": {
      "count": 7,
      "avg_ping_ms": 973.1
    },
    "LU": {
      "count": 2,
      "avg_ping_ms": 795.5
    },
    "LV": {
      "count": 5,
      "avg_ping_ms": 1015.0
    },
    "MD": {
      "count": 3,
      "avg_ping_ms": 687.0
    },
    "MX": {
      "count": 2,
      "avg_ping_ms": 450.5
    },
    "MY": {
      "count": 2,
      "avg_ping_ms": 816.0
    },
    "NL": {
      "count": 210,
      "avg_ping_ms": 640.6
    },
    "NO": {
      "count": 4,
      "avg_ping_ms": 1064.5
    },
    "PH": {
      "count": 2,
      "avg_ping_ms": 792.5
    },
    "PL": {
      "count": 27,
      "avg_ping_ms": 994.4
    },
    "RO": {
      "count": 3,
      "avg_ping_ms": 983.7
    },
    "RS": {
      "count": 6,
      "avg_ping_ms": 991.5
    },
    "RU": {
      "count": 43,
      "avg_ping_ms": 879.0
    },
    "SA": {
      "count": 3,
      "avg_ping_ms": 1255.3
    },
    "SE": {
      "count": 28,
      "avg_ping_ms": 897.6
    },
    "SG": {
      "count": 24,
      "avg_ping_ms": 1108.8
    },
    "SK": {
      "count": 1,
      "avg_ping_ms": 1085.0
    },
    "TH": {
      "count": 3,
      "avg_ping_ms": 1136.7
    },
    "TR": {
      "count": 5,
      "avg_ping_ms": 933.0
    },
    "TW": {
      "count": 5,
      "avg_ping_ms": 743.6
    },
    "UA": {
      "count": 1,
      "avg_ping_ms": 525.0
    },
    "US": {
      "count": 240,
      "avg_ping_ms": 372.5
    },
    "VN": {
      "count": 1,
      "avg_ping_ms": 837.0
    },
    "XX": {
      "count": 2,
      "avg_ping_ms": 635.5
    },
    "ZA": {
      "count": 3,
      "avg_ping_ms": 1200.3
    }
  }
}