{
  "checked_at": "2026-07-23 09:45:41 UTC",
  "total_working": 1900,
  "avg_latency_ms": 656.5,
  "min_latency_ms": 96,
  "avg_speed_mbps": 0,
  "speed_checked": false,
  "countries": {
    "AE": {
      "count": 1,
      "avg_ping_ms": 1326.0
    },
    "AL": {
      "count": 2,
      "avg_ping_ms": 759.0
    },
    "AM": {
      "count": 1,
      "avg_ping_ms": 1405.0
    },
    "AT": {
      "count": 5,
      "avg_ping_ms": 1005.8
    },
    "AU": {
      "count": 24,
      "avg_ping_ms": 939.3
    },
    "BE": {
      "count": 1,
      "avg_ping_ms": 589.0
    },
    "BG": {
      "count": 3,
      "avg_ping_ms": 775.3
    },
    "CA": {
      "count": 18,
      "avg_ping_ms": 504.3
    },
    "CH": {
      "count": 7,
      "avg_ping_ms": 814.1
    },
    "CN": {
      "count": 1,
      "avg_ping_ms": 644.0
    },
    "CZ": {
      "count": 4,
      "avg_ping_ms": 779.2
    },
    "DE": {
      "count": 175,
      "avg_ping_ms": 766.1
    },
    "DK": {
      "count": 1,
      "avg_ping_ms": 928.0
    },
    "EE": {
      "count": 1,
      "avg_ping_ms": 789.0
    },
    "ES": {
      "count": 8,
      "avg_ping_ms": 698.9
    },
    "FI": {
      "count": 24,
      "avg_ping_ms": 954.5
    },
    "FR": {
      "count": 124,
      "avg_ping_ms": 752.1
    },
    "GB": {
      "count": 51,
      "avg_ping_ms": 660.1
    },
    "HK": {
      "count": 47,
      "avg_ping_ms": 1110.4
    },
    "IE": {
      "count": 13,
      "avg_ping_ms": 604.6
    },
    "IN": {
      "count": 9,
      "avg_ping_ms": 1126.8
    },
    "IS": {
      "count": 1,
      "avg_ping_ms": 1040.0
    },
    "IT": {
      "count": 25,
      "avg_ping_ms": 681.2
    },
    "JP": {
      "count": 82,
      "avg_ping_ms": 888.4
    },
    "KR": {
      "count": 59,
      "avg_ping_ms": 1054.7
    },
    "KZ": {
      "count": 1,
      "avg_ping_ms": 975.0
    },
    "LT": {
      "count": 8,
      "avg_ping_ms": 905.4
    },
    "LV": {
      "count": 7,
      "avg_ping_ms": 777.7
    },
    "MD": {
      "count": 1,
      "avg_ping_ms": 1187.0
    },
    "MX": {
      "count": 2,
      "avg_ping_ms": 346.0
    },
    "NL": {
      "count": 203,
      "avg_ping_ms": 696.9
    },
    "NO": {
      "count": 3,
      "avg_ping_ms": 1002.7
    },
    "PH": {
      "count": 25,
      "avg_ping_ms": 1320.2
    },
    "PL": {
      "count": 52,
      "avg_ping_ms": 859.8
    },
    "RO": {
      "count": 3,
      "avg_ping_ms": 863.7
    },
    "RU": {
      "count": 38,
      "avg_ping_ms": 774.6
    },
    "SA": {
      "count": 2,
      "avg_ping_ms": 1182.0
    },
    "SC": {
      "count": 1,
      "avg_ping_ms": 687.0
    },
    "SE": {
      "count": 20,
      "avg_ping_ms": 993.6
    },
    "SG": {
      "count": 62,
      "avg_ping_ms": 1102.0
    },
    "TH": {
      "count": 2,
      "avg_ping_ms": 1257.0
    },
    "TR": {
      "count": 28,
      "avg_ping_ms": 1158.4
    },
    "TW": {
      "count": 8,
      "avg_ping_ms": 839.2
    },
    "US": {
      "count": 736,
      "avg_ping_ms": 363.6
    },
    "XX": {
      "count": 9,
      "avg_ping_ms": 766.1
    },
    "ZA": {
      "count": 2,
      "avg_ping_ms": 1208.0
    }
  }
}