{
  "checked_at": "2026-06-27 14:47:18 UTC",
  "total_working": 1490,
  "avg_latency_ms": 612.1,
  "min_latency_ms": 55,
  "avg_speed_mbps": 0,
  "speed_checked": false,
  "countries": {
    "AE": {
      "count": 1,
      "avg_ping_ms": 1238.0
    },
    "AL": {
      "count": 2,
      "avg_ping_ms": 715.0
    },
    "AM": {
      "count": 1,
      "avg_ping_ms": 833.0
    },
    "AT": {
      "count": 3,
      "avg_ping_ms": 717.7
    },
    "AU": {
      "count": 6,
      "avg_ping_ms": 890.0
    },
    "BE": {
      "count": 1,
      "avg_ping_ms": 597.0
    },
    "BR": {
      "count": 2,
      "avg_ping_ms": 560.5
    },
    "BY": {
      "count": 1,
      "avg_ping_ms": 813.0
    },
    "CA": {
      "count": 21,
      "avg_ping_ms": 375.5
    },
    "CH": {
      "count": 34,
      "avg_ping_ms": 879.7
    },
    "CO": {
      "count": 1,
      "avg_ping_ms": 440.0
    },
    "CZ": {
      "count": 1,
      "avg_ping_ms": 705.0
    },
    "DE": {
      "count": 148,
      "avg_ping_ms": 636.5
    },
    "EE": {
      "count": 3,
      "avg_ping_ms": 770.3
    },
    "ES": {
      "count": 7,
      "avg_ping_ms": 652.7
    },
    "FI": {
      "count": 29,
      "avg_ping_ms": 724.4
    },
    "FR": {
      "count": 73,
      "avg_ping_ms": 711.2
    },
    "GB": {
      "count": 40,
      "avg_ping_ms": 541.1
    },
    "GE": {
      "count": 5,
      "avg_ping_ms": 530.2
    },
    "GR": {
      "count": 1,
      "avg_ping_ms": 916.0
    },
    "HK": {
      "count": 31,
      "avg_ping_ms": 984.5
    },
    "HU": {
      "count": 55,
      "avg_ping_ms": 555.6
    },
    "IE": {
      "count": 4,
      "avg_ping_ms": 527.8
    },
    "IL": {
      "count": 1,
      "avg_ping_ms": 691.0
    },
    "IN": {
      "count": 3,
      "avg_ping_ms": 841.7
    },
    "IS": {
      "count": 1,
      "avg_ping_ms": 884.0
    },
    "IT": {
      "count": 42,
      "avg_ping_ms": 476.3
    },
    "JP": {
      "count": 87,
      "avg_ping_ms": 1016.0
    },
    "KR": {
      "count": 31,
      "avg_ping_ms": 1158.6
    },
    "KZ": {
      "count": 3,
      "avg_ping_ms": 1237.0
    },
    "LT": {
      "count": 148,
      "avg_ping_ms": 462.8
    },
    "LU": {
      "count": 2,
      "avg_ping_ms": 578.0
    },
    "LV": {
      "count": 4,
      "avg_ping_ms": 907.8
    },
    "MD": {
      "count": 1,
      "avg_ping_ms": 675.0
    },
    "MX": {
      "count": 1,
      "avg_ping_ms": 433.0
    },
    "MY": {
      "count": 2,
      "avg_ping_ms": 1211.0
    },
    "NL": {
      "count": 102,
      "avg_ping_ms": 550.6
    },
    "PH": {
      "count": 1,
      "avg_ping_ms": 1214.0
    },
    "PK": {
      "count": 1,
      "avg_ping_ms": 791.0
    },
    "PL": {
      "count": 16,
      "avg_ping_ms": 708.7
    },
    "RO": {
      "count": 2,
      "avg_ping_ms": 477.5
    },
    "RS": {
      "count": 2,
      "avg_ping_ms": 624.0
    },
    "RU": {
      "count": 19,
      "avg_ping_ms": 834.6
    },
    "SA": {
      "count": 1,
      "avg_ping_ms": 1260.0
    },
    "SE": {
      "count": 9,
      "avg_ping_ms": 737.9
    },
    "SG": {
      "count": 43,
      "avg_ping_ms": 1035.0
    },
    "TH": {
      "count": 1,
      "avg_ping_ms": 836.0
    },
    "TR": {
      "count": 20,
      "avg_ping_ms": 605.9
    },
    "TW": {
      "count": 4,
      "avg_ping_ms": 945.0
    },
    "US": {
      "count": 232,
      "avg_ping_ms": 335.8
    },
    "XX": {
      "count": 238,
      "avg_ping_ms": 547.2
    },
    "ZA": {
      "count": 3,
      "avg_ping_ms": 1149.0
    }
  }
}